scalable/Dockerfile
scalable/__init__.py
scalable/_version.py
scalable/caching.py
scalable/client.py
scalable/common.py
scalable/core.py
scalable/custom_types.py
scalable/scalable_bootstrap.sh
scalable/slurm.py
scalable/support.py
scalable/utilities.py
scalable-1.0.0.dist-info/LICENSE.md
scalable-1.0.0.dist-info/METADATA
scalable-1.0.0.dist-info/WHEEL
scalable-1.0.0.dist-info/entry_points.txt
scalable-1.0.0.dist-info/top_level.txt
scalable-1.0.0.dist-info/RECORD
