Metadata-Version: 2.2
Name: scalable
Version: 1.0.0
Summary: Assist with running models on job queing systems like Slurm
Home-page: https://github.com/JGCRI/scalable
Author-email: Shashank Lamba <shashank.lamba@pnnl.gov>, Pralit Patel <pralit.patel@pnnl.gov>
Maintainer-email: Shashank Lamba <shashank.lamba@pnnl.gov>
License: BSD 2-Clause License
Project-URL: Github, https://github.com/JGCRI/scalable/tree/master/scalable
Classifier: Development Status :: 4 - Beta
Classifier: Intended Audience :: Science/Research
Classifier: Topic :: System :: Distributed Computing
Classifier: License :: OSI Approved :: BSD License
Classifier: Programming Language :: Python :: 3
Classifier: Programming Language :: Python :: 3.9
Classifier: Programming Language :: Python :: 3.10
Classifier: Programming Language :: Python :: 3.11
Classifier: Programming Language :: Python :: 3.12
Classifier: Programming Language :: Python :: 3 :: Only
Requires-Python: >=3.8
License-File: LICENSE.md
Requires-Dist: cryptography>=42.0.8
Requires-Dist: dask>=2022.02.0
Requires-Dist: dill>=0.3.8
Requires-Dist: diskcache>=5.6.3
Requires-Dist: distributed>=2022.02.0
Requires-Dist: joblib>=1.3.2
Requires-Dist: xxhash>=3.4.1
Requires-Dist: versioneer>=0.29
Requires-Dist: numpy>=1.26.4
Requires-Dist: pandas>=2.2.3
Provides-Extra: test
Requires-Dist: cryptography; extra == "test"
Requires-Dist: pytest; extra == "test"
Requires-Dist: pytest-asyncio; extra == "test"
Dynamic: home-page
Dynamic: requires-python
